flask_sqlalchemy_qs/__init__.py
flask_sqlalchemy_qs/qs_parser/main.py
flask_sqlalchemy_qs/query/constants.py
flask_sqlalchemy_qs/query/model.py
flask_sqlalchemy_qs-1.1.5.dist-info/LICENSE
flask_sqlalchemy_qs-1.1.5.dist-info/METADATA
flask_sqlalchemy_qs-1.1.5.dist-info/WHEEL
flask_sqlalchemy_qs-1.1.5.dist-info/top_level.txt
flask_sqlalchemy_qs-1.1.5.dist-info/RECORD
