Metadata-Version: 2.1
Name: flask-sqlalchemy-qs
Version: 1.1.5
Summary: Generate and manipulate SQLAlchemy filters and sorts from query strings in the URL
Home-page: https://github.com/marcogil93/flask-sqlalchemy-qs
Author: Marco Gil
Author-email: marcogil93@gmail.com
License: MIT
Classifier: License :: OSI Approved :: MIT License
Classifier: Programming Language :: Python :: 3.7
Classifier: Operating System :: OS Independent
Classifier: Framework :: Flask
Requires-Python: >=3.7
License-File: LICENSE
Requires-Dist: sqlalchemy (>=2.0)
Requires-Dist: flask (>=2.2)
Requires-Dist: flask-sqlalchemy (>=3.0)
Provides-Extra: dev
Requires-Dist: pytest (>=7.0) ; extra == 'dev'
Requires-Dist: twine (>=4.0) ; extra == 'dev'
